{
    "code": {
        "emoji.py": "import commune as c\n\nclass Emoji(c.Module):\n    @classmethod\n    def emoji(cls,  name:str):\n        emojis = []\n        for k,v in cls.emojis.items():\n            if name in k:\n                emojis += [v]\n   \n        return c.choice(emojis)\n        \n    emojis = {'dank': '\ud83d\udd25',\n            'error': '\ud83d\udca5',\n            'white': '\ud83d\udd4a\ufe0f',\n            'cool': '\ud83d\ude0e',\n            'success': '\u2728',\n            'sad': '\ud83d\ude22',\n            'time': '\ud83d\udd52',\n            'count': '\ud83d\udd22',\n            'output': '\ud83d\udce4',\n            'input': '\ud83d\udce5',\n            'party': '\ud83e\udd73',\n            'fireworks': '\ud83c\udf86',\n            'explosion': '\ud83d\udca3',\n            'alien': '\ud83d\udc7d',\n            'rocket': '\ud83d\ude80',\n            'money': '\ud83d\udcb0',\n            'victory': '\u270c\ufe0f',\n            'unicorn': '\ud83e\udd84',\n            'rainbow': '\ud83c\udf08',\n            'music': '\ud83c\udfb5',\n            'pizza': '\ud83c\udf55',\n            'taco': '\ud83c\udf2e',\n            'sunglasses': '\ud83d\ude0e',\n            'flame': '\ud83d\udd25',\n            'diamond': '\ud83d\udc8e',\n            'savage': '\ud83d\ude08',\n            'laughing': '\ud83d\ude02',\n            'ninja': '\ud83e\udd77',\n            'skull': '\ud83d\udc80',\n            'thumbs_up': '\ud83d\udc4d',\n            'thumbs_down': '\ud83d\udc4e',\n            'crown': '\ud83d\udc51',\n            'cyber_eye': '\ud83d\udc41\ufe0f\u200d\ud83d\udde8\ufe0f',\n            'data_stream': '\ud83c\udf10', \n            'brain': '\ud83e\udde0',\n            'robot': '\ud83e\udd16',\n            'lightning': '\u26a1',\n            'heart': '\u2764\ufe0f',\n            'heartbreak': '\ud83d\udc94',\n            'heartpulse': '\ud83d\udc97',\n            'green_heart': '\ud83d\udc9a',\n            'blue_heart': '\ud83d\udc99',\n            'purple_heart': '\ud83d\udc9c',\n            'yellow_heart': '\ud83d\udc9b',\n            'orange_heart': '\ud83e\udde1',\n            'error': '\ud83d\udca5',\n            'cross': '\u274c',\n            'check': '\u2705',\n            'wrong': '\u274c',\n            'right': '\u2705',\n            'correct': '\u2705',\n            'incorrect': '\u274c',\n            'checkmark': '\u2705',\n            'check_mark': '\u2705',\n            'checkered_flag': '\ud83c\udfc1',\n            'warning': '\u26a0\ufe0f',\n            'warning_sign': f'\u26a0\ufe0f',\n            'question': '\u2753',\n            'happy': '\ud83d\ude00',\n            'sad': '\ud83d\ude22',\n            'angry': '\ud83d\ude20',\n            'angry_face': '\ud83d\ude20',\n            'angry_face_with_horns': '\ud83d\udc7f',\n            'devil': '\ud83d\ude08',\n            'red_circle': '\ud83d\udd34',\n            'green_circle': '\ud83d\udfe2',\n            'blue_circle': '\ud83d\udd35',\n            'yellow_circle': '\ud83d\udfe1',\n            'orange_circle': '\ud83d\udfe0',\n            'purple_circle': '\ud83d\udfe3',\n            'black_circle': '\u26ab',\n            'white_circle': '\u26aa',\n            'brown_circle': '\ud83d\udfe4',\n            'red_square': '\ud83d\udfe5',\n            'green_square': '\ud83d\udfe9',\n            'blue_square': '\ud83d\udfe6',\n            'yellow_square': '\ud83d\udfe8',\n            'orange_square': '\ud83d\udfe7',\n            'purple_square': '\ud83d\udfea',\n            'black_square': '\u2b1b',\n            'white_square': '\u2b1c',\n            'brown_square': '\ud83d\udfeb',\n            'satellite': '\ud83d\udef0\ufe0f',\n            'satellite_antenna': '\ud83d\udce1',\n            'computer': '\ud83d\udcbb',\n            \n    }\n\n"
    },
    "schema": {
        "emoji": {
            "input": {
                "name": {
                    "value": "_empty",
                    "type": "_empty"
                }
            },
            "output": {
                "value": null,
                "type": "None"
            },
            "docs": null,
            "cost": 1,
            "name": "emoji",
            "source": {
                "start": 4,
                "length": 8,
                "path": "~/commune/commune/modules/emoji/emoji.py",
                "code": null,
                "hash": "sha256:8f966c86f96181a1314764e960d9b3c041feefb822ed86721a359bd88cefd971",
                "end": 12
            }
        }
    },
    "name": "emoji",
    "key": "5FvckGuyBrxQxns5cvK5yLY9PnV8cU16HFz1nZWPCxuF7U6W",
    "founder": "5GKvu9qC8VPjXnofUxZP6zxTmvzTBCY1vpJAkh6gWF8YxPKy",
    "cid": "sha256:d1a057dd4d0853b7252493342159cdd2d45a66dab66b698fcdc20d392bb7fc15",
    "time": 1746536218.833864,
    "signature": "0x0cb8685ba4b8edcf88effc53fdb1cacb3438492446f8810fa5f191a7b09db0068a772005ffa175885c288d105c7d9de51eeabc8a5780dc23d1c4cfadffa1f185"
}